transform/__init__.py
transform/process.py
transform/augmentation/__init__.py
transform/augmentation/adjust_gamma_aug.py
transform/augmentation/augmentation.py
transform/augmentation/auto_orient.py
transform/augmentation/blur_aug.py
transform/augmentation/brightness_aug.py
transform/augmentation/contrast_equalization_aug.py
transform/augmentation/crop_aug.py
transform/augmentation/cutout_aug.py
transform/augmentation/flip_aug.py
transform/augmentation/grayscale_aug.py
transform/augmentation/hsl.py
transform/augmentation/hue_aug.py
transform/augmentation/labeled_image.py
transform/augmentation/mosaic_aug.py
transform/augmentation/noise_aug.py
transform/augmentation/random_crop_aug.py
transform/augmentation/resize_aug.py
transform/augmentation/rotate_aug.py
transform/augmentation/saturation_aug.py
transform/augmentation/select_annotation_aug.py
transform/augmentation/shear_aug.py
transform/augmentation/split_data.py
transform/augmentation/static_crop_aug.py
transform/augmentation/tile_aug.py
transform/helper/__init__.py
transform/helper/bounds.py
transform/helper/crop_to_center.py
transform/helper/draw_annotations.py
transform/helper/polygon.py
transform/helper/rectangle_conversion.py
transform/helper/round_half.py
transform/helper/trim_annotations.py
transform/helper/warpAffine.py
augmentations-0.0.1.dist-info/METADATA
augmentations-0.0.1.dist-info/WHEEL
augmentations-0.0.1.dist-info/top_level.txt
augmentations-0.0.1.dist-info/RECORD
