Metadata-Version: 2.1
Name: augmentations
Version: 0.0.1
Summary: Roboflow Augmentations PIP Package
Author: Roboflow
Author-email: jim@roboflow.com
Classifier: Programming Language :: Python :: 3.10
Requires-Dist: wheel
Requires-Dist: Cython (>=0.29.0)
Requires-Dist: numpy (>=1.23.0)
Requires-Dist: scikit-image (>=0.19.0)
Requires-Dist: pillow (>=9.0.1)
Requires-Dist: geojson (>=2.5.0)
Requires-Dist: scipy (>=1.9.1)
Requires-Dist: Shapely (>=1.8.4)
Requires-Dist: turfpy (>=0.0.7)
Requires-Dist: rasterio (>=1.3.0)
